AUTHORS.rst
CONTRIBUTING.rst
HISTORY.rst
LICENSE
MANIFEST.in
README.rst
setup.py
bigger/__init__.py
bigger/decorators.py
bigger/draw.py
bigger/encoding.py
bigger/lamination.py
bigger/mappingclassgroup.py
bigger/structures.py
bigger/triangulation.py
bigger/types.py
bigger/utilities.py
bigger.egg-info/PKG-INFO
bigger.egg-info/SOURCES.txt
bigger.egg-info/dependency_links.txt
bigger.egg-info/not-zip-safe
bigger.egg-info/requires.txt
bigger.egg-info/top_level.txt
bigger/fonts/FreeMonoBold.ttf
bigger/load/__init__.py
bigger/load/cantor.py
bigger/load/flute.py
bigger/load/ladder.py
bigger/load/lochness.py
bigger/load/utils.py
docs/Makefile
docs/conf.py
docs/index.rst
docs/api/bigger.rst
docs/dev/authors.rst
docs/dev/contributing.rst
docs/dev/philosophy.rst
docs/dev/todo.rst
docs/images/biflute.png
docs/images/biflute_layout.png
docs/images/biflute_weights.png
docs/images/ladder.png
docs/templates/summary.rst
docs/user/citing.rst
docs/user/history.rst
docs/user/install.rst
docs/user/intro.rst
docs/user/surfaces.rst
docs/user/walkthrough.rst
tests/conftest.py
tests/regression.py
tests/structures.py