Metadata-Version: 1.1
Name: bigger
Version: 0.3.0
Summary: For studying big mapping classes
Home-page: https://github.com/MarkCBell/bigger
Author: Mark Bell
Author-email: mcbell@illinois.edu
License: MIT License
Keywords: infinite surface MCG
Platform: UNKNOWN
Classifier: Development Status :: 4 - Beta
Classifier: Intended Audience :: Education
Classifier: Intended Audience :: Science/Research
Classifier: License :: OSI Approved :: MIT License
Classifier: Natural Language :: English
Classifier: Operating System :: OS Independent
Classifier: Programming Language :: Python
Classifier: Topic :: Scientific/Engineering :: Mathematics
